{
  "levels": [
    {
      "level": "",
      "mode": "default",
      "rows": [
        [
          [
            "q"
          ],
          [
            "w"
          ],
          [
            "e",
            "├й",
            "├и",
            "├л",
            "├к",
            "─Щ",
            "─Ч",
            "─У"
          ],
          [
            "r"
          ],
          [
            "t"
          ],
          [
            "y"
          ],
          [
            "u",
            "├║",
            "├╝",
            "├╣",
            "├╗",
            "┼л"
          ],
          [
            "i",
            "├н",
            "├п",
            "├м",
            "├о",
            "─п",
            "─л"
          ],
          [
            "o",
            "├│",
            "├▓",
            "├╢",
            "├┤",
            "├╡",
            "├╕",
            "┼У",
            "┼Н",
            "┬║"
          ],
          [
            "p"
          ]
        ],
        [
          [
            "a",
            "├б",
            "├а",
            "├д",
            "├в",
            "├г",
            "├е",
            "─Е",
            "├ж",
            "─Б",
            "┬к"
          ],
          [
            "s"
          ],
          [
            "d"
          ],
          [
            "f"
          ],
          [
            "g"
          ],
          [
            "h"
          ],
          [
            "j"
          ],
          [
            "k"
          ],
          [
            "l"
          ],
          [
            "├▒"
          ]
        ],
        [
          [
            "z"
          ],
          [
            "x"
          ],
          [
            "c",
            "├з",
            "─З",
            "─Н"
          ],
          [
            "v"
          ],
          [
            "b"
          ],
          [
            "n",
            "├▒",
            "┼Д"
          ],
          [
            "m"
          ]
        ],
        [
          [
            ","
          ],
          [
            " "
          ],
          [
            ".",
            ";",
            "!",
            ",",
            "?",
            ":",
            "┬б",
            "@",
            "┬┐"
          ]
        ]
      ]
    },
    {
      "level": "shift",
      "mode": "latched",
      "rows": [
        [
          [
            "Q"
          ],
          [
            "W"
          ],
          [
            "E",
            "├Й",
            "├И",
            "├Л",
            "├К",
            "─Ш",
            "─Ц",
            "─Т"
          ],
          [
            "R"
          ],
          [
            "T"
          ],
          [
            "Y"
          ],
          [
            "U",
            "├Ъ",
            "├Ь",
            "├Щ",
            "├Ы",
            "┼к"
          ],
          [
            "I",
            "├Н",
            "├П",
            "├М",
            "├О",
            "─о",
            "─к"
          ],
          [
            "O",
            "├У",
            "├Т",
            "├Ц",
            "├Ф",
            "├Х",
            "├Ш",
            "┼Т",
            "┼М",
            "┬║"
          ],
          [
            "P"
          ]
        ],
        [
          [
            "A",
            "├Б",
            "├А",
            "├Д",
            "├В",
            "├Г",
            "├Е",
            "─Д",
            "├Ж",
            "─А",
            "┬к"
          ],
          [
            "S"
          ],
          [
            "D"
          ],
          [
            "F"
          ],
          [
            "G"
          ],
          [
            "H"
          ],
          [
            "J"
          ],
          [
            "K"
          ],
          [
            "L"
          ],
          [
            "├С"
          ]
        ],
        [
          [
            "Z"
          ],
          [
            "X"
          ],
          [
            "C",
            "├З",
            "─Ж",
            "─М"
          ],
          [
            "V"
          ],
          [
            "B"
          ],
          [
            "N",
            "├С",
            "┼Г"
          ],
          [
            "M"
          ]
        ],
        [
          [
            ","
          ],
          [
            " "
          ],
          [
            ".",
            ";",
            "!",
            ",",
            "?",
            ":",
            "┬б",
            "@",
            "┬┐"
          ]
        ]
      ]
    },
    {
      "level": "opt",
      "mode": "locked",
      "rows": [
        [
          [
            "1",
            "┬╣",
            "┬╜",
            "тЕУ",
            "┬╝",
            "тЕЫ"
          ],
          [
            "2",
            "┬▓",
            "тЕФ"
          ],
          [
            "3",
            "┬│",
            "┬╛",
            "тЕЬ"
          ],
          [
            "4",
            "тБ┤"
          ],
          [
            "5",
            "тЕЭ"
          ],
          [
            "6"
          ],
          [
            "7",
            "тЕЮ"
          ],
          [
            "8"
          ],
          [
            "9"
          ],
          [
            "0",
            "тБ┐",
            "тИЕ"
          ]
        ],
        [
          [
            "@"
          ],
          [
            "#"
          ],
          [
            "$",
            "┬в",
            "┬г",
            "тВм",
            "┬е",
            "тВ▒"
          ],
          [
            "%",
            "тА░"
          ],
          [
            "&"
          ],
          [
            "-",
            "_",
            "тАУ",
            "тАФ",
            "┬╖"
          ],
          [
            "+",
            "┬▒"
          ],
          [
            "(",
            "<",
            "{",
            "["
          ],
          [
            ")",
            ">",
            "}",
            "]"
          ]
        ],
        [
          [
            "*",
            "тАа",
            "тАб",
            "тШЕ"
          ],
          [
            "\"",
            "тАЬ",
            "тАЭ",
            "┬л",
            "┬╗"
          ],
          [
            "'",
            "тАШ",
            "тАЩ",
            "тА╣",
            "тА║"
          ],
          [
            ":"
          ],
          [
            ";"
          ],
          [
            "!",
            "┬б"
          ],
          [
            "?",
            "┬┐"
          ]
        ],
        [
          [
            "_"
          ],
          [
            "/"
          ],
          [
            " "
          ],
          [
            ",",
            "!",
            "┬б"
          ],
          [
            ".",
            "?",
            "┬┐"
          ]
        ]
      ]
    },
    {
      "level": "opt+shift",
      "mode": "locked",
      "rows": [
        [
          [
            "~"
          ],
          [
            "`"
          ],
          [
            "|"
          ],
          [
            "тАв",
            "тЩк",
            "тЩе",
            "тЩа",
            "тЩж",
            "тЩг"
          ],
          [
            "тИЪ"
          ],
          [
            "╬а",
            "╧А"
          ],
          [
            "├╖"
          ],
          [
            "├Ч"
          ],
          [
            "┬╢",
            "┬з"
          ],
          [
            "тИЖ"
          ]
        ],
        [
          [
            "┬г"
          ],
          [
            "┬в"
          ],
          [
            "тВм"
          ],
          [
            "┬е"
          ],
          [
            "^",
            "тЖС",
            "тЖУ",
            "тЖР",
            "тЖТ"
          ],
          [
            "┬░",
            "тА▓",
            "тА│"
          ],
          [
            "=",
            "тЙа",
            "тЙИ",
            "тИЮ"
          ],
          [
            "{"
          ],
          [
            "}"
          ]
        ],
        [
          [
            "\\"
          ],
          [
            "┬й"
          ],
          [
            "┬о"
          ],
          [
            "тДв"
          ],
          [
            "тДЕ"
          ],
          [
            "["
          ],
          [
            "]"
          ]
        ],
        [
          [
            "<",
            "тА╣",
            "тЙд",
            "┬л"
          ],
          [
            ">",
            "тА║",
            "тЙе",
            "┬╗"
          ],
          [
            " "
          ],
          [
            ",",
            "!",
            "┬б"
          ],
          [
            ".",
            "?",
            "┬┐"
          ]
        ]
      ]
    }
  ],
  "locale": "es-US",
  "name": "Spanish United States"
}